{
	"name": "Glacia",
	"version": 1,
	"element": "water",
	"kick": "up",
	"target": "very front",
	"rarity": 5,
	"dmg_type": "magic",
	"ability": null,
	"birthday": { "month": 7, "day": 2 },
	"attributes": {
		"initial_combat_power": 260,
		"crit_rate": 10,
		"crit_dmg": 50,
		"def": 0,
		"magic_resist": 20,
		"prop_dmg": 50,
		"prop_resist": 50,
		"hp": {
			"min": 255,
			"max": 4473
		},
		"atk": {
			"min": 11,
			"max": 110
		}
	},
	"exclusive_gear": {
		"name": "Frost Queen",
		"ability": "Magic Resist%",
		"basic_stat": "Magic ATK"
	},
	"costumes": ["Alice", "Disciplinary Committee"]
}
